meteaudata/__init__.py
meteaudata/display_utils.py
meteaudata/displayable.py
meteaudata/graph_display.py
meteaudata/tree_builder.py
meteaudata/types.py
meteaudata/processing_steps/multivariate/average.py
meteaudata/processing_steps/univariate/interpolate.py
meteaudata/processing_steps/univariate/prediction.py
meteaudata/processing_steps/univariate/replace.py
meteaudata/processing_steps/univariate/resample.py
meteaudata/processing_steps/univariate/subset.py
meteaudata/templates/__init__.py
meteaudata/templates/svg_graph_template.html
meteaudata-0.9.2.dist-info/METADATA
meteaudata-0.9.2.dist-info/WHEEL
meteaudata-0.9.2.dist-info/licenses/LICENSE
meteaudata-0.9.2.dist-info/RECORD
