Metadata-Version: 2.4
Name: meteaudata
Version: 0.9.2
Summary: A lightweight package for tracking metadata about time series to create repeatable data pipelines.
Project-URL: Homepage, https://github.com/modelEAU/meteaudata
Project-URL: Documentation, https://modeleau.github.io/meteaudata/
Author-email: Jean-David Therrien <jeandavidt@gmail.com>
License: CC-BY4
License-File: LICENSE
Requires-Python: >=3.9
Requires-Dist: ipython<9.0.0,>=8.2.0
Requires-Dist: ipywidgets>=8.1.7
Requires-Dist: networkx>=3.2.1
Requires-Dist: pandas>=1.4
Requires-Dist: plotly<6.0.0,>=5.21.0
Requires-Dist: pydantic<3.0,>=2.0
Requires-Dist: pyyaml<7.0.0,>=6.0.1
